cooper_epic_jungle/__init__.py
cooper_epic_jungle/cooper_epic_jungle/epic/EPT/encounters/ambulatory/information/info_ambulatory_encounter_dx.sql
cooper_epic_jungle/cooper_epic_jungle/epic/EPT/encounters/ambulatory/population/generic.sql
cooper_epic_jungle/cooper_epic_jungle/epic/EPT/encounters/billing/information/encounter_payor.sql
cooper_epic_jungle/cooper_epic_jungle/epic/EPT/encounters/billing/information/info_enc_based_professional_billing.sql
cooper_epic_jungle/cooper_epic_jungle/epic/EPT/encounters/general/information/get_revenue_location.sql
cooper_epic_jungle/cooper_epic_jungle/epic/EPT/encounters/general/population/pop_adt_events.sql
cooper_epic_jungle/cooper_epic_jungle/epic/EPT/encounters/general/population/pop_cpt_date_based_encounters.sql
cooper_epic_jungle/cooper_epic_jungle/epic/EPT/encounters/hospital/information/info_hospital_encounter_dx.sql
cooper_epic_jungle/cooper_epic_jungle/epic/EPT/encounters/hospital/information/opat_patient_encounters.sql
cooper_epic_jungle/cooper_epic_jungle/epic/EPT/encounters/hospital/population/hsp_obs_ip_encounters.sql
cooper_epic_jungle/cooper_epic_jungle/epic/EPT/encounters/hospital/population/pop_ed_encs.sql
cooper_epic_jungle/cooper_epic_jungle/epic/EPT/encounters/hospital/population/pop_scheduled_surgeries_by_date.sql
cooper_epic_jungle/cooper_epic_jungle/epic/EPT/encounters/hospital/population/pop_surgeries_by_date.sql
cooper_epic_jungle/cooper_epic_jungle/epic/EPT/encounters/notes/information/provider_notes.sql
cooper_epic_jungle/cooper_epic_jungle/epic/EPT/patient/demographics/information/demographics.sql
cooper_epic_jungle/cooper_epic_jungle/epic/EPT/patient/demographics/information/info_patient_languages.sql
cooper_epic_jungle/cooper_epic_jungle/epic/EPT/patient/demographics/information/patient_demographics.sql
cooper_epic_jungle/cooper_epic_jungle/epic/EPT/patient/general/information/info_patid_from_mrn.sql
cooper_epic_jungle/cooper_epic_jungle/epic/EPT/patient/general/information/mrn_from_patid.sql
cooper_epic_jungle-2.0.1.dist-info/METADATA
cooper_epic_jungle-2.0.1.dist-info/WHEEL
cooper_epic_jungle-2.0.1.dist-info/RECORD
