Metadata-Version: 2.3
Name: cooper-epic-jungle
Version: 2.0.1
Summary: An extension of the mipi package. Contains a repository of sql scripts and functions to build modular reports using them
Author: murphy-sean1
Author-email: murphy-sean1@cooperhealth.edu
Requires-Python: >=3.12,<4.0
Classifier: Programming Language :: Python :: 3
Classifier: Programming Language :: Python :: 3.12
Classifier: Programming Language :: Python :: 3.13
Requires-Dist: bump-my-version (>=1.2.1,<2.0.0)
Requires-Dist: mipi-datamanager (>=1.3.5,<2.0.0)
